setup.cfg
setup.py
Pojen.egg-info/PKG-INFO
Pojen.egg-info/SOURCES.txt
Pojen.egg-info/dependency_links.txt
Pojen.egg-info/entry_points.txt
Pojen.egg-info/top_level.txt
pojen/__init__.py
pojen/builders.py
pojen/engine.py
pojen/file_handler.py
pojen/json_parser.py
tests/__init__.py
tests/test_builders.py
tests/test_engine.py
tests/test_parser.py